ife/__init__.py
ife/data/__init__.py
ife/data/small_rgb.jpg
ife/data/strawberry.jpg
ife/features/__init__.py
ife/features/colourfulness.py
ife/features/features.py
ife/features/moment.py
ife/features/tests/__init__.py
ife/features/tests/test_colourfulness.py
ife/features/tests/test_features.py
ife/features/tests/test_moment.py
ife/io/__init__.py
ife/io/io.py
ife/io/tests/__init__.py
ife/io/tests/test_io.py
ife/util/__init__.py
ife/util/array.py
ife/util/tests/__init__.py
ife/util/tests/test_array.py
ife-0.0.3.dist-info/LICENSE
ife-0.0.3.dist-info/WHEEL
ife-0.0.3.dist-info/METADATA
ife-0.0.3.dist-info/RECORD
