Metadata-Version: 2.1
Name: ife
Version: 0.0.3
Summary: You can get a nice global image feature!
Home-page: https://github.com/Collonville/ImageFeatureExtractor
License: BSD-3-Clause
Author: HokutoTateyama
Author-email: ht235711@yahoo.co.jp
Requires-Python: >=3.6,<4.0
Classifier: Development Status :: 2 - Pre-Alpha
Classifier: License :: OSI Approved :: BSD License
Classifier: Programming Language :: Python :: 3
Classifier: Programming Language :: Python :: 3 :: Only
Classifier: Programming Language :: Python :: 3.6
Classifier: Programming Language :: Python :: 3.7
Classifier: Topic :: Scientific/Engineering
Requires-Dist: Pillow (>=6.1,<7.0)
Requires-Dist: colour-science (>=0.3.13,<0.4.0)
Requires-Dist: pandas (>=0.25.0,<0.26.0)
Project-URL: Repository, https://github.com/Collonville/ImageFeatureExtractor
